<!DOCTYPE ui:UiBinder SYSTEM "http://dl.google.com/gwt/DTD/xhtml.ent">

<ui:UiBinder xmlns:ui='urn:ui:com.google.gwt.uibinder'
	xmlns:g='urn:import:com.google.gwt.user.client.ui' ui:generateFormat='com.google.gwt.i18n.rebind.format.PropertiesFormat'
	ui:generateKeys='com.google.gwt.i18n.rebind.keygen.MD5KeyGenerator'
	ui:generateLocales='default'>
	<ui:style>
	#main-menu .nav-bar {
		list-style: none;
		margin-top: 40px;
	}
	
	#main-menu .nav-bar li {
		float: right;
		display: inline;
		padding: 0 10px;
	}
	
	#main-menu .nav-bar li a {
		text-decoration: none;
		padding-left: 25px;
		text-transform: uppercase;
		color: #333;
		text-shadow: 1px 1px 1px #ccc;
	}
	
	.nav-bar .nav-button-home a {
		background:
			url("http://www.cheesetoast.co.uk/cheesepress/wp-content/uploads/2012/08/home.gif")
			no-repeat 0px -2px transparent;
	}
	
	.nav-bar .nav-button-services a {
		background:
			url("http://www.cheesetoast.co.uk/cheesepress/wp-content/uploads/2012/08/services.gif")
			no-repeat 0px -2px transparent;
	}
	
	.nav-bar .nav-button-products a {
		background:
			url("http://www.cheesetoast.co.uk/cheesepress/wp-content/uploads/2012/08/products.gif")
			no-repeat 0px -2px transparent;
	}
	</ui:style>

	<g:HTMLPanel>
		<nav id="main-menu">
			<ul class="nav-bar">
				<li class="nav-button-home">
					<a href="#">Home</a>
				</li>
				<li class="nav-button-services">
					<a href="#">Services</a>
				</li>
				<li class="nav-button-products">
					<a href="#">Products</a>
				</li>
			</ul>
		</nav>
	</g:HTMLPanel>
</ui:UiBinder>
